{"id":153669,"link":"https://chinadigitaltimes.net/chinese/2011/05/脱去了新装，中国怎么办_一品高官_新浪博客/","date":"2011-05-20T09:00:58Z","modified":"2011-05-20T09:00:58Z","title":"脱去了新装，中国怎么办_一品高官_新浪博客","content":"<p>由重庆导演出来的李庄案已经被视为中国<b>法治</b>史上的臭名昭著的事件，从中折射出现有制度下<b>司法独立</b>的艰难，以及中国司法随时都会面临的困局。然而，从积极的角度看，这个事件的持续发展却可以让人清晰的分辨出：究竟谁在真正的维护中国法律。 <b>&#8230;.</b> 中充当护法的 英雄，负责监督、维护法律的是全国人大下属的各类组织机构，维护律师权益的有中华全国律师协会，危难时刻，这些组织怎么能无动于衷呢？4月19日，李庄遗漏罪在重庆江北法院正式开庭审理，到底是<b>人治</b>还是<b>法治</b>，是依法治国还是无法无天，我们将拭目以待。 &#8230;</p>\n<p><small>本文由自动聚合程序取自网络，内容和观点不代表数字时代立场</small></p>\n<form method=\"POST\" action=\"http://www.feedblitz.com/f/f.fbz?AddNewUserDirect\">\n定期获得翻墙信息？<a href=\"http://www.feedblitz.com/f/?Sub=750556\">请电邮订阅数字时代</a> <br /><input name=\"EMAIL\" maxlength=\"64\" type=\"text\" size=\"25\" value=\"\"><br />\n<input name=\"FEEDID\" type=\"hidden\" value=\"750556\"><br />\n<input name=\"PUBLISHER\" type=\"hidden\" value=\"7485568\"><br />\n<input type=\"submit\" value=\"订阅!\"><br />\n</form>\n","author":176,"categories":[9203],"tags":[9239,13958]}