{"id":257060,"link":"https://chinadigitaltimes.net/chinese/2012/10/中央社-日媒：大陸軍官在東京參加研討/","date":"2012-10-15T10:00:32Z","modified":"2012-10-15T10:00:32Z","title":"中央社 | 日媒：大陸軍官在東京參加研討","content":"<div>\n<p><span>加入中央社粉絲團</span>   </p>\n<p>16:09:13</p>\n<div>\n<p>（中央社台北15日電）日本媒體報導，來自中國大陸的軍官今天在東京參加由日本海上自衛隊主辦的國際海上安全保障與救難研討會。這是釣魚台爭議以來，第1個到日本訪問的大陸軍方代表團。</p>\n<p>日本新聞網的報導說，大陸軍方代表團以年輕軍官為主，上午在日本海上自衛隊幹部學校出席研討會開幕儀式。</p>\n<p>報導說，這項研討為期10天，大陸的人員將與其他19個國家的軍官一起，研討海上救難和海洋安全保障等問題，並將參觀日本的護衛艦和海上救難訓練。</p>\n<p>另據日本放送協會（NHK）指出，這個研討會去年起舉辦，目的在增進日本海上自衛隊與亞太各國海軍的交流。今年，來自美國、加拿大、澳洲等19國的20名年輕海軍軍官出席會議。</p>\n<p>日本海上自衛隊幹部學校副校長山本敏弘在致詞時表示，他堅信面對面的交談溝通必能增進相互理解，構築信賴關係。1011015</p>\n</div>\n</div>\n<p><img src=\"http://pixel.quantserve.com/pixel/p-89EKCgBk8MZdE.gif\" border=\"0\" height=\"1\" width=\"1\" /></p>\n<p><small>本文由自动聚合程序取自网络，内容和观点不代表数字时代立场</small></p>\n<p><iframe src=\"https://docs.google.com/a/chinadigitaltimes.net/spreadsheet/embeddedform?hl=zh-CN&#038;formkey=dGlaNkplWEluYV9TWUxDQkhfaDlxQmc6MQ\" width=\"510\" height=\"334\" frameborder=\"0\" marginheight=\"0\" marginwidth=\"0\">Loading&#8230;</iframe></p>\n<form method=\"POST\" action=\"http://chinadigitaltimes.us4.list-manage.com/subscribe/post?u=17daa75df533f6c6ff72e51ab&#038;id=2ea93c5b7b\">\n<a href=\"http://eepurl.com/msuvD\">墙外新闻实时更新 欢迎订阅数字时代</a><br />\n <br /><input type=\"email\" value=\"\" name=\"EMAIL\" id=\"mce-EMAIL_in_post\" size=\"25\" style=\"display:block;\" placeholder=\"请输入您的邮件地址\" required><br />\n\t<input type=\"submit\" value=\"点击订阅\" name=\"subscribe\" style=\"height: 20px;\" id=\"in_post_subscribe\"><br />\n</form>\n","author":1000,"categories":[18270,18269,18424],"tags":[19188]}