{"id":263613,"link":"https://chinadigitaltimes.net/chinese/2012/11/［舒立观察］改革此其时/","date":"2012-11-17T15:45:14Z","modified":"2012-11-17T15:45:14Z","title":"［舒立观察］改革此其时","content":"<p>新旧交接之际，经济上恰恰出现改革窗口。改与不改，对在任与下任的领导者们的使命感、责任心和执政能力，其实都是重大考验</p>\n<p>从经济视角看，中共十八大落幕或许赶上了好时候：经济增长持续低于市场预期的局面正在改变。新近公布的经济数据显示，工业、投资、消费、出口等增长类指标，均连续两月呈现回升态势，中国经济短期下滑之势已经得到遏制。</p>\n<p>相较2008年应对金融危机，决策者此次对经济增速下滑的认识更为冷静客观：一方面是容忍度明显提高，对出台新一轮经济刺激措施颇为谨慎；另一方面，在“稳增长”的同时不忘改革，要求“把稳增长与抓改革联系起来”。这是一个好迹象。</p>\n<p>需要强调的是，当下经济企稳，绝  <a href=\"http://hushuli.blog.caixin.com/archives/48914\">阅读全文</a></p>\n<p><small>本文由自动聚合程序取自网络，内容和观点不代表数字时代立场</small></p>\n<p><iframe src=\"https://docs.google.com/spreadsheet/embeddedform?hl=zh-CN&#038;formkey=dGRpN3FrVThuMFFsZHBZcmNGLW94dEE6MQ\" width=\"510\" height=\"328\" frameborder=\"0\" marginheight=\"0\" marginwidth=\"0\">Loading&#8230;</iframe></p>\n<form method=\"POST\" action=\"http://chinadigitaltimes.us4.list-manage.com/subscribe/post?u=17daa75df533f6c6ff72e51ab&#038;id=2ea93c5b7b\">\n<a href=\"http://eepurl.com/msuvD\">墙外新闻实时更新 欢迎订阅数字时代</a><br />\n <br /><input type=\"email\" value=\"\" name=\"EMAIL\" id=\"mce-EMAIL_in_post\" size=\"25\" style=\"display:block;\" placeholder=\"请输入您的邮件地址\" required><br />\n\t<input type=\"submit\" value=\"点击订阅\" name=\"subscribe\" style=\"height: 20px;\" id=\"in_post_subscribe\"><br />\n</form>\n","author":1004,"categories":[18270,18269,9203],"tags":[16912,20975,20977,9184,20023,8724,20976]}