{"id":273629,"link":"https://chinadigitaltimes.net/chinese/2013/01/明報-鐵道部多個局職位提前變動2335/","date":"2013-01-08T23:45:26Z","modified":"2013-01-08T23:45:26Z","title":"明報 | 鐵道部多個局職位提前變動[23:35]","content":"<p><p>21世紀經濟報道稱，離2013年全國兩會召開尚有兩個多月之際，鐵道部人事調整已經啟動。</p>\n<div>\n<p>鐵道部內部人士稱，鐵道部近日多個局級崗位負責人發生變動，是盛光祖自2011年2月走馬上任鐵道部部長以來變動最大的一次。</p>\n<p>1月4日晚，上海鐵路局召開電視電話會議，會上宣布，2011年7·23事故中從鐵道部總調度長任上空降到上海鐵路局擔任局長的安路生離開上海奔赴北京，擔任鐵科院院長。新舊職務級別相同，但鐵科院的職權肯定沒有上海局大。</p>\n<p>另外，南昌局局長郭竹學調任上海局局長，昆明局局長劉振方調任南昌局局長，昆明局黨委書記劉柏盛任昆明局局長。</p>\n<p>自安路生於2011年7月23日調離鐵道部總調度長崗位，此職一直空缺，此次武漢鐵路局局長余卓民將赴京填補這一空缺，西安局局長汪亞平則將到武漢接替餘的位置，蘭州局劉生榮則調任西安局局長。</p>\n<p>鐵道部將呼和浩特局局長楊育棟調任北京局局長，濟南局常務副局長費東斌則接任呼和浩特局局長。</p>\n<p>除各大地方路局外，鐵道部直屬機關也發生重大人事變動，接替因腐敗被雙規、素有高鐵第一人之稱的張曙光，擔任鐵道部運輸局局長的吳強在此次人事變動中被調到政治部擔任副主任，其職位由其副手程先東接任。鐵道部人事司副司長曲林也扶正成為司長。</p>\n<p>（21世紀經濟報道）</p>\n</div>\n<p><img src=\"http://pixel.quantserve.com/pixel/p-89EKCgBk8MZdE.gif\" border=\"0\" height=\"1\" width=\"1\" /></p>\n<p><small>本文由自动聚合程序取自网络，内容和观点不代表数字时代立场</small></p>\n<p><iframe src=\"https://docs.google.com/a/chinadigitaltimes.net/spreadsheet/embeddedform?hl=zh-CN&#038;formkey=dFc0V1d0REQ4RkJ5d25uWFowVTNhWUE6MQ\" width=\"510\" height=\"328\" frameborder=\"0\" marginheight=\"0\" marginwidth=\"0\">Loading&#8230;</iframe></p>\n<form method=\"POST\" action=\"http://chinadigitaltimes.us4.list-manage.com/subscribe/post?u=17daa75df533f6c6ff72e51ab&#038;id=2ea93c5b7b\">\n<a href=\"http://eepurl.com/msuvD\">墙外新闻实时更新 欢迎订阅数字时代</a><br />\n <br /><input type=\"email\" value=\"\" name=\"EMAIL\" id=\"mce-EMAIL_in_post\" size=\"25\" style=\"display:block;\" placeholder=\"请输入您的邮件地址\" required><br />\n\t<input type=\"submit\" value=\"点击订阅\" name=\"subscribe\" style=\"height: 20px;\" id=\"in_post_subscribe\"><br />\n</form>\n","author":1000,"categories":[18270,18269,18424],"tags":[5908,19188,19189]}