{"id":309015,"link":"https://chinadigitaltimes.net/chinese/2013/08/自由亚洲-台保钓团体在日本驻台湾代表处门前抗/","date":"2013-08-15T17:45:16Z","modified":"2013-08-15T17:45:16Z","title":"自由亚洲 | 台保钓团体在日本驻台湾代表处门前抗议","content":"<div>\n<p>在台湾，多个响应保钓运动的团体，周四上午聚集在日本驻台湾代表处门口，通过演说及各种仪式抗议日本占据钓鱼岛。</p>\n<p>周四上午十点，由「台湾钓鱼台光复会」等多个民间团体发起的示威集会在日本驻台机构「交流协会」台北办公室外举行。百馀名群众到场响应。民间团体公推曾任民进党籍立法委员的张俊宏主持集会。</p>\n<p>张俊宏首先发表了讲话。他说今天是八月十五日，是日本投降纪念日。我们到这里，面对着日本交流协会。要进行非常严肃的抗议，告诉日本，如果情势再发展下去，只会引起中日间第二场甲午战争。张俊宏宣称，这场战争，绝对不是当年那样的局部战争，而是一场核子毁灭的战争。</p>\n<p>前新党籍立法委员钱达也强调。保钓团体要警告全世界，也要警告台湾同胞。这场战争一旦爆发，造成的破坏和毁灭实在太可怕。唯一化解冲突，走向和平之道，是把钓鱼岛主权归还给中华民国台湾，这才是唯一的「和平解答」。</p>\n<p>「钓鱼台光复会」理事长、台湾东吴大学教授刘源俊从历史角度切入说明钓鱼台问题。</p>\n<p>刘源俊说，美国在1972年片面决定将琉球及钓鱼岛送给日本，如今又将它入美日安保的范围内。可见一切都是美国主导。日本只是美国的鹰犬。但话说回来，何以美国这个不在东亚的国家，却能取得东亚的发言权，根本原因还是日本侵略美国在先，轰炸珍珠港，最后落败。所以为东亚「引狼入室」的罪魁祸首，还是日本。</p>\n<p>参与示威集会的民众准备了各式各样的道具，演讲者在宣传车上演讲时，有人开始用棍子敲打一个写着「日本鬼子」的半身假人。主办单位也准备了一个西瓜，贴上日本首相安倍的照片，然后再由参与示威的原住民代表，以其传统的「出草」，也就是猎人头的仪式，用猎刀砍杀这颗西瓜，象征猎下安倍的人头。</p>\n<p>最后，主办单位推出一艘纸扎的道具船，上头写着「出云号」，跟着一把火把它烧个精光，象徵抵抗日本军国主义再起。</p>\n<p>另一方面，台湾外交部周四针对日本总务大臣新藤义孝及防灾大臣古屋圭司参拜靖国神社发表声明。</p>\n<p>外交部强调，中华民国政府盼日本政府及政治人物正视史实并记取历史教训，切勿做出伤害邻近国家国民情感的举措。外交部说，盼望日本政府能以前瞻性的思维，负责任的态度，与周边国家发展友好关係。</p>\n<p>以上是自由亚洲电台记者李潼发自台北的报道。</p>\n</div>\n<p><img src=\"http://pixel.quantserve.com/pixel/p-89EKCgBk8MZdE.gif\" border=\"0\" height=\"1\" width=\"1\" /></p>\n<p><small>本文由自动聚合程序取自网络，内容和观点不代表数字时代立场</small></p>\n<p><iframe src=\"https://docs.google.com/spreadsheet/embeddedform?hl=zh-CN&#038;formkey=dGRpN3FrVThuMFFsZHBZcmNGLW94dEE6MQ\" width=\"510\" height=\"326\" frameborder=\"0\" marginheight=\"0\" marginwidth=\"0\">Loading&#8230;</iframe></p>\n<form method=\"POST\" action=\"http://chinadigitaltimes.us4.list-manage.com/subscribe/post?u=17daa75df533f6c6ff72e51ab&#038;id=b4fd4ae247\">\n<a href=\"http://eepurl.com/mstlf\">墙外新闻实时更新 欢迎订阅数字时代 </a><br />\n <br /><input type=\"email\" value=\"\" name=\"EMAIL\" id=\"mce-EMAIL_in_post\" size=\"25\" style=\"display:block;\" placeholder=\"请输入您的邮件地址\" required><br />\n\t<input type=\"submit\" value=\"点击订阅\" name=\"subscribe\" style=\"height: 20px;\" id=\"in_post_subscribe\"><br />\n</form>\n","author":998,"categories":[18270,18269,8779],"tags":[19188,8639,9826]}