{"id":318835,"link":"https://chinadigitaltimes.net/chinese/2013/10/自由亚州｜鸡西警方：抓捕唐吉田律师是中央政法/","date":"2013-10-19T20:55:37Z","modified":"2013-10-19T20:55:37Z","title":"自由亚州｜鸡西警方：抓捕唐吉田律师是中央政法委下的命令","content":"<p>据“中国公民维权联盟”星期六发布的消息，目前被黑龙江鸡西市当局以“扰乱办公秩序罪” 行政拘留的北京律师唐吉田，当天经押送鸡西市第二看守所后，曾被看守所方面以唐律师身患肺结核、未经痰检而拒绝收押。唐律师随后在鸡西传染病医院做完痰检，再次被国保人员送往看守所关押。报道说，目前已抵达当地的董前勇律师证实，鸡西市鸡冠区公安分局郑姓局长明确表示，鸡西市公安局已就该案上报黑龙江省“610办公室”及中央政法委。中央政法委明确指示，唐吉田不是一般的律师，不能放人。</p>\n<p><small>本文由自动聚合程序取自网络，内容和观点不代表数字时代立场</small></p>\n<form action=\"http://chinadigitaltimes.us4.list-manage.com/subscribe/post?u=17daa75df533f6c6ff72e51ab&amp;id=b4fd4ae247\" method=\"POST\"><a href=\"http://eepurl.com/mstlf\">墙外新闻实时更新 欢迎订阅数字时代</a></p>\n<p><input id=\"mce-EMAIL_in_post\" style=\"display: block;\" type=\"email\" name=\"EMAIL\" placeholder=\"请输入您的邮件地址\" required=\"\" size=\"25\" value=\"\" /><br />\n<input id=\"in_post_subscribe\" style=\"height: 20px;\" type=\"submit\" name=\"subscribe\" value=\"点击订阅\" /></p>\n</form>\n","author":1002,"categories":[18270,18269,8779],"tags":[19194,14981]}