{"id":330655,"link":"https://chinadigitaltimes.net/chinese/2014/01/台灣新聞-人權團體批美-偵監是錯誤示範/","date":"2014-01-21T18:04:02Z","modified":"2014-01-21T18:04:02Z","title":"台灣新聞 | 人權團體批美 偵監是錯誤示範","content":"<p><div>（中央社柏林21日綜合外電報導）人權觀察執行主任羅思告訴路透社，美國總統歐巴馬宣示改革國家安全局（NSA）大規模偵監計畫，但改革不徹底、仍持續侵害個人隱私權，無異為別國做出錯誤示範。</p>\n<p>歐巴馬17日發表演說，公布偵監計畫改革方案。</p>\n<p>設在紐約的人權觀察（Human Rights Watch）今天發布年度全球人權報告，表示美國國家安全局不尊重隱私權，將替壓制性國家提供一塊遮羞布，壓制表現自由。</p>\n<p>報告說：「結果是，如果隱私權被視為嚴格國內議題，則隱私將無處安全，會有許多例外情況且只有鬆散或根本不存在監督機制。」</p>\n<p>人權觀察主管羅思（Kenneth Roth）在柏林的訪談中說：「歐巴馬所做的，只不過是若干模糊的保證，說如果涉及國家安全顧慮，則個人通訊將被監聽。國安是相當模糊的廣泛標準。」</p>\n<p>羅思說：「（他的話中）完全沒承認美國境外的非美國公民也享有個人通訊…和詮釋資料（metadata）的隱私權，也沒承認每個人都有權利不讓自己的電子通訊被截入政府電腦中。」</p>\n<p>他說，並無證據顯示，大規模搜集通訊能顯著改善安全狀態。</p>\n<p>這份厚達667頁的年度報告是在柏林發布的，涵蓋世界超過90國人權狀況，今年是第24年發布年度報告。</p>\n<p>這份報告指出，由於世界大半網際網路會「經過美國領土或透過美國公司」，因此美國政府處於「監控全球通訊特別有利地位」，也因此特別有責任要守護相關權利。</p>\n<p>羅思告訴法新社，中國大陸、俄羅斯和印度都會師法美國國安局的作業綱領，來侵害個人權利。</p>\n<p>羅思說，人權觀察之所以選柏林來發布年度報告，是因為國安局偵監計畫去年夏季遭揭露後，柏林是全球怒火的引爆點。1030121</p>\n</div>\n<p><img src=\"http://pixel.quantserve.com/pixel/p-89EKCgBk8MZdE.gif\" border=\"0\" height=\"1\" width=\"1\"></p>\n</p>\n<p><small>本文由自动聚合程序取自网络，内容和观点不代表数字时代立场</small></p>\n<p><iframe src=\"https://docs.google.com/spreadsheet/embeddedform?hl=zh-CN&#038;formkey=dGRpN3FrVThuMFFsZHBZcmNGLW94dEE6MQ\" width=\"510\" height=\"326\" frameborder=\"0\" marginheight=\"0\" marginwidth=\"0\">Loading&#8230;</iframe></p>\n<form method=\"POST\" action=\"http://chinadigitaltimes.us4.list-manage.com/subscribe/post?u=17daa75df533f6c6ff72e51ab&#038;id=2ea93c5b7b\">\n<a href=\"http://eepurl.com/msuvD\">墙外新闻实时更新 欢迎订阅数字时代</a><br />\n <br /><input type=\"email\" value=\"\" name=\"EMAIL\" id=\"mce-EMAIL_in_post\" size=\"25\" style=\"display:block;\" placeholder=\"请输入您的邮件地址\" required><br />\n\t<input type=\"submit\" value=\"点击订阅\" name=\"subscribe\" style=\"height: 20px;\" id=\"in_post_subscribe\"><br />\n</form>\n","author":1000,"categories":[18270,18269,18424],"tags":[8641,11945]}