{"id":351292,"link":"https://chinadigitaltimes.net/chinese/2014/06/美国之音-焦点对话李克强访英，中国用钱堵人权/","date":"2014-06-20T15:48:47Z","modified":"2014-06-20T15:48:47Z","title":"美国之音 | 焦点对话:李克强访英，中国用钱堵人权？","content":"<p><div><span>&#21326;&#30427;&#39039;</span> &mdash; &#20013;&#22269;&#24635;&#29702;&#26446;&#20811;&#24378;19&#21495;&#32467;&#26463;&#23545;&#33521;&#22269;&#20026;&#26102;&#19977;&#22825;&#30340;&#35775;&#38382;&#12290;&#36825;&#26159;&#20004;&#22269;2012&#24180;&#22240;&#20026;&#36798;&#36182;&#21895;&#22043;&#35775;&#33521;&#20135;&#29983;&#20998;&#27495;&#20043;&#21518;&#65292;&#20013;&#22269;&#24635;&#29702;&#39318;&#27425;&#35775;&#38382;&#33521;&#22269;&#12290;&#26446;&#20811;&#24378;&#35775;&#33521;&#20043;&#38469;&#65292;&#20013;&#33521;&#20004;&#22269;&#31614;&#32626;&#20102;140&#20159;&#33521;&#38225;&#30340;&#21830;&#19994;&#21512;&#21516;&#65307;&#20013;&#22269;&#28023;&#27915;&#30707;&#27833;&#24635;&#20844;&#21496;&#19982;&#33521;&#22269;&#30707;&#27833;&#20844;&#21496;&#65288;&#31616;&#31216;BP&#20844;&#21496;&#65289;&#31614;&#32626;&#21327;&#35758;&#65292;&#36827;&#19968;&#27493;&#21457;&#23637;&#20840;&#29699;&#21512;&#20316;&#12290;&#26446;&#20811;&#24378;&#31216;&#65292;&#26399;&#24453;&#27492;&#34892;&#33021;&#22815;&#25913;&#21464;&#33521;&#22269;&#23545;&#20013;&#22269;&#30340;&#35823;&#35299;&#21644;&#25285;&#24551;&#65307;&#33521;&#22269;&#21017;&#35828;&#65292;&#23427;&#20173;&#28982;&#23545;&#20013;&#22269;&#20154;&#26435;&#29366;&#20917;&ldquo;&#28145;&#24863;&#25285;&#24551;&rdquo;&#12290;&#37027;&#20040;&#65292;&#20013;&#22269;&#26159;&#21542;&#26399;&#24453;&#36890;&#36807;&#29992;&#37329;&#38065;&#35746;&#21333;&#36141;&#20080;&#20154;&#26435;&#38382;&#39064;&#30340;&#24310;&#21518;&#22788;&#29702;&#65311;&#21253;&#25324;&#33521;&#22269;&#22312;&#20869;&#30340;&#35199;&#26041;&#19990;&#30028;&#22914;&#20309;&#22788;&#21033;&#30410;&#21644;&#20154;&#26435;&#36825;&#23545;&#40060;&#19982;&#29066;&#25484;&#20043;&#38388;&#30340;&#20851;&#31995;&#65311;</p>\n<p>&#21442;&#21152;&#36825;&#27425;&#35752;&#35770;&#30340;&#22025;&#23486;&#26159;&#65306;&#26222;&#26519;&#26031;&#39039;&#20013;&#22269;&#23398;&#31038;&#25191;&#34892;&#20027;&#24109;&#38472;&#22862;&#24503;&#65292; &#32654;&#22269;&#21152;&#22270;&#30740;&#31350;&#25152;&#35775;&#38382;&#30740;&#31350;&#21592;&#22799;&#19994;&#33391;&#65292;&#20316;&#23478;&#12289;&#25919;&#27835;&#35780;&#35770;&#23478;&#38472;&#30772;&#31354;&#20197;&#21450;&#26222;&#26519;&#26031;&#39039;&#22823;&#23398;&#23398;&#32773;&#31243;&#26195;&#20892;&#12290; </p>\n<h5>&#28966;&#28857;&#23545;&#35805;&#65306;&#26446;&#20811;&#24378;&#35775;&#33521;&#65292;&#20013;&#22269;&#29992;&#37329;&#38065;&#22581;&#20154;&#26435;&#65311;</h5>\n<div>\n<div>\n<div>\n<div>\n<div>\n<div></div>\n</div>\n<div><span>&#28966;&#28857;&#23545;&#35805;&#65306;&#26446;&#20811;&#24378;&#35775;&#33521;&#65292;&#20013;&#22269;&#29992;&#37329;&#38065;&#22581;&#20154;&#26435;&#65311;</span><a rel=\"nofollow\" target=\"_blank\" href=\"http://fullrss.net/r/javascript/www.voachinese.com/content/voaweishi-0620-pro-and-con-2/void(0)\"><span>i</span></a></div>\n<div>\n<div>\n<div>\n<div></div>\n<div></div>\n</div>\n<p><button><span>&#9654;</span></button></div>\n<div><a rel=\"nofollow\" target=\"_blank\" href=\"http://fullrss.net/r/javascript/www.voachinese.com/content/voaweishi-0620-pro-and-con-2/void(0)\">&#9654;</a> <a rel=\"nofollow\" target=\"_blank\" href=\"http://fullrss.net/r/javascript/www.voachinese.com/content/voaweishi-0620-pro-and-con-2/void(0)\">||</a> <span>0:00:00</span></div>\n<div><a rel=\"nofollow\" target=\"_blank\" href=\"http://fullrss.net/r/javascript/www.voachinese.com/content/voaweishi-0620-pro-and-con-2/void(0)\">&#8230;</a> <a rel=\"nofollow\" name=\"ab42eff240ca44b2dbeed4efeee7b0cb5_h5t_hylFullscreen\">&#8689;</a> <a rel=\"nofollow\" target=\"_blank\" href=\"http://fullrss.net/r/http/www.voachinese.com/emailtofriend/audio/Audio/424357.html?isflashembed=true\" name=\"ab42eff240ca44b2dbeed4efeee7b0cb5_h5t_hylShare\"></a></p>\n<ul></ul>\n<p><a rel=\"nofollow\" target=\"_blank\" href=\"http://fullrss.net/r/javascript/www.voachinese.com/content/voaweishi-0620-pro-and-con-2/void(0)\"> </a></p>\n<div></div>\n<p><a rel=\"nofollow\" target=\"_blank\" href=\"http://fullrss.net/r/javascript/www.voachinese.com/content/voaweishi-0620-pro-and-con-2/void(0)\">&#128263;</a></p>\n<div>\n<div>\n<div></div>\n</div>\n<p><button><span>&#9654;</span></button></div>\n</div>\n</div>\n<div>\n<div></div>\n<div>\n<div>&#9654;</div>\n</div>\n</div>\n<div>\n<div><a rel=\"nofollow\" target=\"_blank\" href=\"http://fullrss.net/r/javascript/www.voachinese.com/content/voaweishi-0620-pro-and-con-2/void(0)\">X</a></p>\n<div></div>\n<div></div>\n<div></div>\n</div>\n</div>\n</div>\n<div></div>\n</div>\n</div>\n</div>\n<ul>\n<li><a rel=\"nofollow\" target=\"_blank\" href=\"http://fullrss.net/r/javascript/www.voachinese.com/content/voaweishi-0620-pro-and-con-2/opened=winOpened();%20if%20(!opened)%20window.__playerWindow%20=%20window.open(winUrl(4,'424357',false),winName(),winSettings);%20winSetup(4,'424357',false,%20opened);\">&#25773;&#25918;</a></li>\n<li><a rel=\"nofollow\" target=\"_blank\" href=\"http://fullrss.net/r/http/av.voanews.com/clips/CHIN/2014/06/20/fa955b23-72c3-484e-923c-03b1677aae1a.mp3\">&#19979;&#36733;</a></li>\n</ul>\n<p><strong>YouTube&#38142;&#25509;: </strong><a rel=\"nofollow\" target=\"_blank\" href=\"http://fullrss.net/r/https/www.youtube.com/watch?v=i33bNTtKvGU\">&#28966;&#28857;&#23545;&#35805;&#65306;&#26446;&#20811;&#24378;&#35775;&#33521;&#65292;&#20013;&#22269;&#29992;&#37329;&#38065;&#22581;&#20154;&#26435;&#65311;</a></p>\n<div><a rel=\"nofollow\" target=\"_blank\" href=\"http://fullrss.net/r/http/bit.ly/JiaoDian-youtube\"><img border=\"0\" src=\"http://gdb.voanews.com/6409A1B8-D053-484D-9153-664E4432F988_w268.png\"></a></div>\n</div>\n<p><img border=\"0\" src=\"http://gdb.voanews.com/6409A1B8-D053-484D-9153-664E4432F988_w268.png\"></p>\n<div><img src=\"http://fullrss.net/v/b5751a1dab57f57671c5d503ab58280b/http/www.voachinese.com/content/voaweishi-0620-pro-and-con-2/1941449.html\"></div>\n<div><a rel=\"nofollow\" target=\"_blank\" href=\"http://fullrss.net/\">fullrss.net</a></div>\n</p>\n<p><small>本文由自动聚合程序取自网络，内容和观点不代表数字时代立场</small></p>\n","author":998,"categories":[18270,18269,8779],"tags":[20431,12012]}