{"id":65948,"link":"https://chinadigitaltimes.net/chinese/2010/05/上海世博，究竟应“搏”什么？/","date":"2010-05-03T18:30:14Z","modified":"2010-05-03T18:30:14Z","title":"上海世博，究竟应“搏”什么？","content":"<p><span lang=\"EN-US\" style=\"font-size:12pt;color:black\"></p>\n<p align=\"left\" style=\"margin:0cm 0cm 0pt;text-indent:21pt;line-height:16pt;text-align:left\"><span lang=\"EN-US\" style=\"font-size:12pt;color:black\">2010</span><span style=\"font-size:12pt;color:black\">年<span lang=\"EN-US\">4</span>月<span lang=\"EN-US\">30</span>日晚，当绚丽的礼花在黄浦江畔升起绽放，整个国家精心准备了<span lang=\"EN-US\">8</span>年之久的上海世界博览会终于拉开了帷幕。大陆官媒一致称赞，说是中华民族融入世界的梦想做了<span lang=\"EN-US\">100</span>多年，终于在这一刻实现；中国人又一次高扬了民族自豪感。“这既是第一次在发展中国家举办的世博会，也是历史上规模最大的一次世博盛会”。</span></p>\n<p align=\"left\" style=\"margin:0cm 0cm 0pt;text-indent:21pt;line-height:16pt;text-align:left\"><span style=\"font-size:12pt;color:black\">大陆的专家学者早已告诉国人，世博会对一座城市和一个国家拉动消费、改善基础设施、促进经济腾飞都有莫大的刺激作用，他们还列举了日本、澳大利亚等国成功办博的许多例子。还有人试图通过<span lang=\"EN-US\">1851</span>年英国举办第一届万国博览会以来<span lang=\"EN-US\">160</span>年历史来证明，一届成功的世博会往往与一个国家的“崛起”呈现惊人的匹配。因此，上海世博 ……</p>\n<p>……</span></p>\n<p align=\"left\" style=\"margin:0cm 0cm 0pt;text-indent:21pt;line-height:16pt;text-align:left\">\n<p align=\"left\" style=\"background:white;margin:0cm 0cm 0pt;text-indent:24pt;line-height:16pt;text-align:left\">\n<p align=\"left\" style=\"background:white;margin:0cm 0cm 0pt;text-indent:24pt;line-height:16pt;text-align:left\">\n<p align=\"left\" style=\"background:white;margin:0cm 0cm 0pt;text-indent:24pt;line-height:16pt;text-align:left\">\n<p align=\"left\" style=\"background:white;margin:0cm 0cm 0pt;text-indent:24pt;line-height:16pt;text-align:left\">\n<p align=\"left\" style=\"background:white;margin:0cm 0cm 0pt;text-indent:24pt;line-height:16pt;text-align:left\">\n<p align=\"left\" style=\"background:white;margin:0cm 0cm 0pt;text-indent:24pt;line-height:16pt;text-align:left\">\n<p align=\"left\" style=\"background:white;margin:0cm 0cm 0pt;text-indent:24pt;line-height:16pt;text-align:left\">\n<p align=\"left\" style=\"background:white;margin:0cm 0cm 0pt;text-indent:24pt;line-height:16pt;text-align:left\">\n<p align=\"left\" style=\"background:white;margin:0cm 0cm 0pt;text-indent:24pt;line-height:16pt;text-align:left\">\n<p align=\"left\" style=\"background:white;margin:0cm 0cm 0pt;text-indent:24pt;line-height:16pt;text-align:left\">\n<p align=\"left\" style=\"background:white;margin:0cm 0cm 0pt;text-indent:24pt;line-height:16pt;text-align:left\">\n<p align=\"left\" style=\"background:white;margin:0cm 0cm 0pt;text-indent:24pt;line-height:16pt;text-align:left\">\n<p align=\"left\" style=\"background:white;margin:0cm 0cm 0pt;text-indent:24pt;line-height:16pt;text-align:left\">\n<p align=\"left\" style=\"background:white;margin:0cm 0cm 0pt;text-indent:24pt;line-height:16pt;text-align:left\">\n<p align=\"left\" style=\"background:white;margin:0cm 0cm 0pt;text-indent:24pt;line-height:16pt;text-align:left\">\n<p align=\"left\" style=\"background:white;margin:0cm 0cm 0pt;text-indent:24pt;line-height:16pt;text-align:left\">\n<p align=\"left\" style=\"background:white;margin:0cm 0cm 0pt;text-indent:24pt;line-height:16pt;text-align:left\">\n<p align=\"left\" style=\"background:white;margin:0cm 0cm 0pt;text-indent:24pt;line-height:16pt;text-align:left\">\n<p align=\"left\" style=\"background:white;margin:0cm 0cm 0pt;text-indent:24pt;line-height:16pt;text-align:left\">\n<p align=\"left\" style=\"margin:0cm 0cm 0pt;text-indent:21pt;line-height:16pt;text-align:left\">\n</p>\n</p>\n</p>\n</p>\n</p>\n</p>\n</p>\n</p>\n</p>\n</p>\n</p>\n<p></span></p>\n<p align=\"left\" style=\"background:white;margin:0cm 0cm 0pt;text-indent:24pt;line-height:16pt;text-align:left\"><span style=\"font-size:12pt;color:black\"></p>\n<p align=\"left\" style=\"margin:0cm 0cm 0pt;text-indent:24pt;line-height:16pt;text-align:left\"><span style=\"font-size:12pt;color:black\"><span style=\"font-size:12pt;color:black\"><span style=\"font-size:12pt;color:black\"><span style=\"font-size:12pt;color:black\"><span style=\"font-size:12pt;color:black\"><span style=\"font-size:12pt;color:black\"><span><span style=\"font-size:12pt;color:black\"><span style=\"font-size:12pt;color:black\"><span style=\"font-size:12pt;color:black\"><span lang=\"EN-US\" style=\"font-size:12pt\"></p>\n<p align=\"left\" style=\"margin:0cm 0cm 0pt;text-indent:24pt;text-align:left\">\n<p align=\"left\" style=\"margin:0cm 0cm 0pt;text-indent:24pt;text-align:left\">\n<p align=\"left\" style=\"margin:0cm 0cm 0pt;text-indent:24pt;text-align:left\">\n<p align=\"left\" style=\"margin:0cm 0cm 0pt;text-indent:24pt;text-align:left\"><span style=\"font-size:12pt;color:black\"><span style=\"font-size:12pt;color:black\"><span lang=\"EN-US\" style=\"font-size:12pt;color:black\"><span style=\"font-size:12pt\"><span style=\"font-size:12pt;color:black\"><span style=\"font-size:12pt;color:black\"></p>\n<p style=\"background:white;margin:0cm 0cm 0pt;text-indent:24pt;text-align:left\">\n<p style=\"background:white;margin:0cm 0cm 0pt;text-indent:24pt;text-align:left\">\n<p style=\"background:white;margin:0cm 0cm 0pt;text-indent:24pt;text-align:left\">\n<p style=\"background:white;margin:0cm 0cm 0pt;text-indent:24pt;text-align:left\">\n<p style=\"background:white;margin:0cm 0cm 0pt;text-indent:24pt;text-align:left\">\n<p style=\"background:white;margin:0cm 0cm 0pt;text-indent:24pt;text-align:left\">\n<p style=\"background:white;margin:0cm 0cm 0pt;text-indent:24pt;text-align:left\">\n</p>\n</p>\n</p>\n<p></span></span></span></span></span></span></p>\n</p>\n</p>\n<p></span></span></span></span></span></span></span></span></span></span></span></p>\n<p></span></p>\n","author":176,"categories":[1],"tags":[9129]}